pycorrfit/PyCorrFit.py
pycorrfit/__init__.py
pycorrfit/__main__.py
pycorrfit/_version.py
pycorrfit/correlation.py
pycorrfit/fit.py
pycorrfit/meta.py
pycorrfit/openfile.py
pycorrfit/trace.py
pycorrfit/gui/__init__.py
pycorrfit/gui/contribute.py
pycorrfit/gui/doc.py
pycorrfit/gui/edclasses.py
pycorrfit/gui/frontend.py
pycorrfit/gui/icon.py
pycorrfit/gui/main.py
pycorrfit/gui/misc.py
pycorrfit/gui/page.py
pycorrfit/gui/plotting.py
pycorrfit/gui/threaded_progress.py
pycorrfit/gui/update.py
pycorrfit/gui/usermodel.py
pycorrfit/gui/wxutils.py
pycorrfit/gui/tools/__init__.py
pycorrfit/gui/tools/average.py
pycorrfit/gui/tools/background.py
pycorrfit/gui/tools/batchcontrol.py
pycorrfit/gui/tools/chooseimport.py
pycorrfit/gui/tools/comment.py
pycorrfit/gui/tools/datarange.py
pycorrfit/gui/tools/example.py
pycorrfit/gui/tools/globalfit.py
pycorrfit/gui/tools/info.py
pycorrfit/gui/tools/overlaycurves.py
pycorrfit/gui/tools/parmrange.py
pycorrfit/gui/tools/plotexport.py
pycorrfit/gui/tools/simulation.py
pycorrfit/gui/tools/statistics.py
pycorrfit/gui/tools/trace.py
pycorrfit/models/MODEL_TIRF_1C.py
pycorrfit/models/MODEL_TIRF_2D2D.py
pycorrfit/models/MODEL_TIRF_3D2D.py
pycorrfit/models/MODEL_TIRF_3D2Dkin_Ries.py
pycorrfit/models/MODEL_TIRF_3D3D.py
pycorrfit/models/MODEL_TIRF_gaussian_1C.py
pycorrfit/models/MODEL_TIRF_gaussian_3D2D.py
pycorrfit/models/MODEL_TIRF_gaussian_3D3D.py
pycorrfit/models/__init__.py
pycorrfit/models/classes.py
pycorrfit/models/control.py
pycorrfit/models/cp_confocal.py
pycorrfit/models/cp_mix.py
pycorrfit/models/cp_triplet.py
pycorrfit/models/model_confocal_2d.py
pycorrfit/models/model_confocal_2d_2d.py
pycorrfit/models/model_confocal_3d.py
pycorrfit/models/model_confocal_3d_2d.py
pycorrfit/models/model_confocal_3d_3d.py
pycorrfit/models/model_confocal_t_2d.py
pycorrfit/models/model_confocal_t_2d_2d.py
pycorrfit/models/model_confocal_t_3d.py
pycorrfit/models/model_confocal_t_3d_2d.py
pycorrfit/models/model_confocal_t_3d_3d.py
pycorrfit-1.3.1.dist-info/licenses/LICENSE
pycorrfit-1.3.1.dist-info/METADATA
pycorrfit-1.3.1.dist-info/WHEEL
pycorrfit-1.3.1.dist-info/entry_points.txt
pycorrfit-1.3.1.dist-info/top_level.txt
pycorrfit-1.3.1.dist-info/RECORD
