Metadata-Version: 2.4
Name: pycorrfit
Version: 1.3.1
Summary: Scientific tool for fitting correlation curves on a logarithmic plot.
Author: Thomas Bischof
Author-email: Paul Müller <dev@craban.de>
License-Expression: GPL-2.0-only
Project-URL: repository, https://github.com/FCS-analysis/PyCorrFit
Keywords: fluorescence correlation spectroscopy (FCS)
Classifier: Operating System :: OS Independent
Classifier: Programming Language :: Python :: 3
Classifier: Topic :: Scientific/Engineering :: Visualization
Classifier: Intended Audience :: Science/Research
Requires-Python: <4,>=3.11
License-File: LICENSE
Requires-Dist: lmfit>=0.9.2
Requires-Dist: numpy>=1.14.2
Requires-Dist: pyyaml>=3.12
Requires-Dist: scipy>=1.0.1
Requires-Dist: ptufile>=2025.12.12
Requires-Dist: looseversion>=1.3.0
Provides-Extra: test
Requires-Dist: pytest; extra == "test"
Requires-Dist: urllib3; extra == "test"
Requires-Dist: ruff; extra == "test"
Requires-Dist: ty; extra == "test"
Requires-Dist: codespell; extra == "test"
Provides-Extra: gui
Requires-Dist: matplotlib>=2.2.2; extra == "gui"
Requires-Dist: sympy>=1.1.1; extra == "gui"
Requires-Dist: simplejson; extra == "gui"
Requires-Dist: wxPython>=4.0.1; extra == "gui"
Dynamic: license-file
